MANIFEST.in
README.md
setup.py
MPPMCTS/MCTS_all.py
MPPMCTS/_MCTS_carbon_test.py
MPPMCTS/__init__.py
MPPMCTS/run.py
MPPMCTS.egg-info/PKG-INFO
MPPMCTS.egg-info/SOURCES.txt
MPPMCTS.egg-info/dependency_links.txt
MPPMCTS.egg-info/entry_points.txt
MPPMCTS.egg-info/requires.txt
MPPMCTS.egg-info/top_level.txt
MPPMCTS/ASDI/SigmaDB.zip
MPPMCTS/ASDI/__init__.py
MPPMCTS/ASDI/asdi.py
MPPMCTS/ASDI/calculate_gamma.py
MPPMCTS/ASDI/to_sigma3.py
MPPMCTS/utils/__init__.py
MPPMCTS/utils/carbon_smiles.py
MPPMCTS/utils/fpscores.pkl.gz
MPPMCTS/utils/meltingpoint.py
MPPMCTS/utils/rnn_model_parameters
MPPMCTS/utils/sascorer.py
MPPMCTS/utils/smiles.py
MPPMCTS/utils/smiles_dict
MPPMCTS/utils/train_model.py